mod_nest_exp/__init__.py
mod_nest_exp/py.typed
mod_nest_exp/benchmarking/__init__.py
mod_nest_exp/benchmarking/benchmark.py
mod_nest_exp/benchmarking/utils.py
mod_nest_exp/core/__init__.py
mod_nest_exp/core/core.py
mod_nest_exp/core/utils.py
mod_nest_exp/core/benchmarks/__init__.py
mod_nest_exp/core/benchmarks/benchmark_core.py
mod_nest_exp/core/tests/__init__.py
mod_nest_exp/core/tests/test_core.py
mod_nest_exp/prelims/__init__.py
mod_nest_exp/prelims/factor.py
mod_nest_exp/prelims/gcd.py
mod_nest_exp/prelims/primes.py
mod_nest_exp/prelims/small_primes.py
mod_nest_exp/prelims/totient.py
mod_nest_exp/prelims/tests/__init__.py
mod_nest_exp-1.1.1.dist-info/LICENSE
mod_nest_exp-1.1.1.dist-info/METADATA
mod_nest_exp-1.1.1.dist-info/WHEEL
mod_nest_exp-1.1.1.dist-info/top_level.txt
mod_nest_exp-1.1.1.dist-info/RECORD
