Metadata-Version: 2.1
Name: mod-nest-exp
Version: 1.1.1
Summary: An algorithm that computes modular nested exponentiation efficiently.
Home-page: https://github.com/avivbrook/modular-nested-exponentiation
Author: Aviv Brook
Author-email: avbrook@ucsc.edu
License: GPLv3
Project-URL: Bug Tracker, https://github.com/avivbrook/modular-nested-exponentiation/issues
Project-URL: Coverage, https://app.codecov.io/gh/avivbrook/modular-nested-exponentiation
Project-URL: CI, https://github.com/avivbrook/modular-nested-exponentiation/actions
Keywords: modular exponentiation,nested exponentiation
Platform: any
Classifier: Topic :: Education
Classifier: Topic :: Scientific/Engineering
Classifier: Topic :: Scientific/Engineering :: Mathematics
Classifier: Topic :: Software Development :: Libraries :: Python Modules
Classifier: Development Status :: 4 - Beta
Classifier: License :: OSI Approved :: GNU General Public License v3 (GPLv3)
Classifier: Programming Language :: Python
Classifier: Programming Language :: Python :: 3
Classifier: Programming Language :: Python :: 3 :: Only
Classifier: Programming Language :: Python :: 3.6
Classifier: Programming Language :: Python :: 3.7
Classifier: Programming Language :: Python :: 3.8
Classifier: Programming Language :: Python :: 3.9
Classifier: Programming Language :: Python :: Implementation :: CPython
Classifier: Operating System :: OS Independent
Classifier: Intended Audience :: Developers
Classifier: Intended Audience :: Education
Classifier: Intended Audience :: Information Technology
Classifier: Intended Audience :: Science/Research
Classifier: Typing :: Typed
Requires-Python: >=3.6
Requires-Dist: setuptools
Provides-Extra: all
Requires-Dist: sympy (~=1.7) ; extra == 'all'
Requires-Dist: gmpy2 (~=2.0) ; extra == 'all'
Requires-Dist: Sphinx (~=3.5) ; extra == 'all'
Provides-Extra: docs
Requires-Dist: Sphinx ; extra == 'docs'
Provides-Extra: gmpy
Requires-Dist: gmpy2 ; extra == 'gmpy'
Provides-Extra: sympy
Requires-Dist: sympy ; extra == 'sympy'
